proxycurl/asyncio/__init__.py
proxycurl/asyncio/base.py
proxycurl/asyncio/library.py
proxycurl/config.py
proxycurl/gevent/__init__.py
proxycurl/gevent/base.py
proxycurl/gevent/library.py
proxycurl/models.py
proxycurl/twisted/__init__.py
proxycurl/twisted/base.py
proxycurl/twisted/library.py
proxycurl_py_dt-0.2.1.dist-info/METADATA
proxycurl_py_dt-0.2.1.dist-info/WHEEL
proxycurl_py_dt-0.2.1.dist-info/RECORD
