Metadata-Version: 2.3
Name: proxycurl-py-dt
Version: 0.2.1
Summary: 
Author: Nubela
Author-email: tech@nubela.co
Requires-Python: >=3.7,<4.0
Classifier: Programming Language :: Python :: 3
Classifier: Programming Language :: Python :: 3.7
Classifier: Programming Language :: Python :: 3.8
Classifier: Programming Language :: Python :: 3.9
Classifier: Programming Language :: Python :: 3.10
Classifier: Programming Language :: Python :: 3.11
Classifier: Programming Language :: Python :: 3.12
Classifier: Programming Language :: Python :: 3.13
Provides-Extra: asyncio
Provides-Extra: gevent
Provides-Extra: twisted
Requires-Dist: Twisted (>=21.7.0,<22.0.0) ; extra == "twisted"
Requires-Dist: aiohttp (>=3.7.4,<4.0.0) ; extra == "asyncio"
Requires-Dist: gevent (>=22.10.2,<23.0.0) ; extra == "gevent"
Requires-Dist: requests (>=2.25.0,<3.0.0) ; extra == "gevent"
Requires-Dist: treq (>=21.5.0,<22.0.0) ; extra == "twisted"
